Yasril/__init__.py
Yasril/Dictionary/ArrayDictionary.py
Yasril/Dictionary/DictionaryInterface.py
Yasril/Dictionary/__init__.py
Yasril/Morphology/InvalidAffixPairSpecification.py
Yasril/Morphology/__init__.py
Yasril/Morphology/Disambiguator/DisambiguatorPrefixRule1.py
Yasril/Morphology/Disambiguator/DisambiguatorPrefixRule10.py
Yasril/Morphology/Disambiguator/DisambiguatorPrefixRule11.py
Yasril/Morphology/Disambiguator/DisambiguatorPrefixRule12.py
Yasril/Morphology/Disambiguator/DisambiguatorPrefixRule13.py
Yasril/Morphology/Disambiguator/DisambiguatorPrefixRule14.py
Yasril/Morphology/Disambiguator/DisambiguatorPrefixRule15.py
Yasril/Morphology/Disambiguator/DisambiguatorPrefixRule16.py
Yasril/Morphology/Disambiguator/DisambiguatorPrefixRule17.py
Yasril/Morphology/Disambiguator/DisambiguatorPrefixRule18.py
Yasril/Morphology/Disambiguator/DisambiguatorPrefixRule19.py
Yasril/Morphology/Disambiguator/DisambiguatorPrefixRule2.py
Yasril/Morphology/Disambiguator/DisambiguatorPrefixRule20.py
Yasril/Morphology/Disambiguator/DisambiguatorPrefixRule21.py
Yasril/Morphology/Disambiguator/DisambiguatorPrefixRule23.py
Yasril/Morphology/Disambiguator/DisambiguatorPrefixRule24.py
Yasril/Morphology/Disambiguator/DisambiguatorPrefixRule25.py
Yasril/Morphology/Disambiguator/DisambiguatorPrefixRule26.py
Yasril/Morphology/Disambiguator/DisambiguatorPrefixRule27.py
Yasril/Morphology/Disambiguator/DisambiguatorPrefixRule28.py
Yasril/Morphology/Disambiguator/DisambiguatorPrefixRule29.py
Yasril/Morphology/Disambiguator/DisambiguatorPrefixRule3.py
Yasril/Morphology/Disambiguator/DisambiguatorPrefixRule30.py
Yasril/Morphology/Disambiguator/DisambiguatorPrefixRule31.py
Yasril/Morphology/Disambiguator/DisambiguatorPrefixRule32.py
Yasril/Morphology/Disambiguator/DisambiguatorPrefixRule34.py
Yasril/Morphology/Disambiguator/DisambiguatorPrefixRule35.py
Yasril/Morphology/Disambiguator/DisambiguatorPrefixRule36.py
Yasril/Morphology/Disambiguator/DisambiguatorPrefixRule37.py
yasril_lib-1.2.0.dist-info/LICENSE
yasril_lib-1.2.0.dist-info/METADATA
yasril_lib-1.2.0.dist-info/WHEEL
yasril_lib-1.2.0.dist-info/top_level.txt
yasril_lib-1.2.0.dist-info/RECORD
